MANIFEST.in
README.md
setup.cfg
setup.py
aguaclara_research/Environmental_Processes_Analysis.py
aguaclara_research/ProCoDA_Parser.py
aguaclara_research/__init__.py
aguaclara_research/floc_model.py
aguaclara_research/play.py
aguaclara_research/tube_sizing.py
aguaclara_research/utils.py
aguaclara_research.egg-info/PKG-INFO
aguaclara_research.egg-info/SOURCES.txt
aguaclara_research.egg-info/dependency_links.txt
aguaclara_research.egg-info/requires.txt
aguaclara_research.egg-info/top_level.txt