Metadata-Version: 1.0
Name: aguaclara-research
Version: 1.0.6
Summary: aguaclara_research
Home-page: https://github.com/AguaClara/aguaclara_research
Author: AguaClara
Author-email: aguaclara@cornell.edu
License: Apache License (2.0)
Platform: UNKNOWN
